media_catalogue/__init__.py
media_catalogue/action_menu.py
media_catalogue/admin.py
media_catalogue/admin_urls.py
media_catalogue/apps.py
media_catalogue/blocks.py
media_catalogue/default_settings.py
media_catalogue/form_fields.py
media_catalogue/formats.py
media_catalogue/forms.py
media_catalogue/image_adapter.py
media_catalogue/layout_blocks.py
media_catalogue/model_porter.py
media_catalogue/other_form_fields.py
media_catalogue/query.py
media_catalogue/rich_text.py
media_catalogue/settings.py
media_catalogue/shortcuts.py
media_catalogue/universal_query.py
media_catalogue/urls.py
media_catalogue/validators.py
media_catalogue/wagtail_hooks.py
media_catalogue/adapters/__init__.py
media_catalogue/adapters/adapter.py
media_catalogue/adapters/registry.py
media_catalogue/editor/__init__.py
media_catalogue/editor/contentstate.py
media_catalogue/migrations/0001_initial.py
media_catalogue/migrations/__init__.py
media_catalogue/models/__init__.py
media_catalogue/models/audit_log.py
media_catalogue/models/errors.py
media_catalogue/models/media_item_fields.py
media_catalogue/models/media_items.py
media_catalogue/models/mixins.py
media_catalogue/models/permissions.py
media_catalogue/models/universal_media_items.py
media_catalogue/models/view_restrictions.py
media_catalogue/static/media_catalogue/css/media_catalogue.css
media_catalogue/static/media_catalogue/css/media_catalogue_admin.css
media_catalogue/templates/media_catalogue/_file_field.html
media_catalogue/templates/media_catalogue/_file_field_as_li.html
media_catalogue/templates/media_catalogue/_header_with_history.html
media_catalogue/templates/media_catalogue/add.html
media_catalogue/templates/media_catalogue/confirm_delete.html
media_catalogue/templates/media_catalogue/create.html
media_catalogue/templates/media_catalogue/create_v3.html
media_catalogue/templates/media_catalogue/edit.html
media_catalogue/templates/media_catalogue/edit_v3.html
media_catalogue/templates/media_catalogue/media_type_selection.html
media_catalogue-4.1.2.dist-info/AUTHORS.txt
media_catalogue-4.1.2.dist-info/LICENSE.txt
media_catalogue-4.1.2.dist-info/METADATA
media_catalogue-4.1.2.dist-info/WHEEL
media_catalogue-4.1.2.dist-info/top_level.txt
media_catalogue-4.1.2.dist-info/RECORD
